pixeldrain_reloaded/Async.py
pixeldrain_reloaded/Sync.py
pixeldrain_reloaded/__init__.py
pixeldrain_reloaded-0.3.dist-info/LICENSE
pixeldrain_reloaded-0.3.dist-info/METADATA
pixeldrain_reloaded-0.3.dist-info/WHEEL
pixeldrain_reloaded-0.3.dist-info/top_level.txt
pixeldrain_reloaded-0.3.dist-info/RECORD
