Metadata-Version: 2.1
Name: pixeldrain-reloaded
Version: 0.3
Summary: Interact with Pixeldrain using Python Synchronously and Asynchronously!
Author: Sliwka
Project-URL: Homepage, https://github.com/s-liwka/pixeldrain-reloaded
Classifier: Programming Language :: Python :: 3
Classifier: License :: OSI Approved :: MIT License
Classifier: Operating System :: OS Independent
Classifier: Development Status :: 3 - Alpha
Classifier: Intended Audience :: Developers
License-File: LICENSE
Requires-Dist: aiohttp
Requires-Dist: requests
Requires-Dist: aiofiles
